{
    "scores": [
        {
            "name": "Test",
            "score": 50,
            "time": 18
        },
        {
            "name": "Test",
            "score": 0,
            "time": 9
        },
        {
            "name": "NULL",
            "score": -1,
            "time": -1
        },
        {
            "name": "NULL",
            "score": -1,
            "time": -1
        },
        {
            "name": "NULL",
            "score": -1,
            "time": -1
        }
    ]
}